dbt_snapshot_analysis.py
dbt_snapshot_analysis/__init__.py
dbt_snapshot_analysis/data_validation.py
dbt_snapshot_analysis/dbt_snapshot_analysis.py
dbt_snapshot_analysis/snapshot_utils.py
dbt_snapshot_analysis/streamlit_entry_point.py
dbt_snapshot_analytics/__init__.py
dbt_snapshot_analytics/dbt_snapshot_analysis.py
dbt_snapshot_analytics/streamlit_entry_point.py
lib/__init__.py
lib/data_validation.py
lib/snapshot_utils.py
dbt_snapshot_analysis-0.2.13.dist-info/METADATA
dbt_snapshot_analysis-0.2.13.dist-info/WHEEL
dbt_snapshot_analysis-0.2.13.dist-info/entry_points.txt
dbt_snapshot_analysis-0.2.13.dist-info/top_level.txt
dbt_snapshot_analysis-0.2.13.dist-info/RECORD
