Metadata-Version: 2.1
Name: dbt-snapshot-analysis
Version: 0.2.13
Summary: A package for analyzing snapshots
Home-page: https://github.com/data-drift/data-drift/tree/main/tools/dbt-snapshot-analysis
Author: Sammy Teillet
Author-email: sammy.teillet@gmail.com
Classifier: Programming Language :: Python :: 3
Classifier: License :: OSI Approved :: MIT License
Classifier: Operating System :: OS Independent
Requires-Dist: pandas
Requires-Dist: plotly
Requires-Dist: streamlit
